{
  "lastUpdate": "2025-07-06",
  "campaigns": [
    {
      "name": "Drive Retention_New Ads",
      "campaignId": "72a6eac0-9cb5-4b5b-9dc4-d8fe26a742d7",
      "startDate": "2025-06-16",
      "endDate": "2025-06-22",
      "objective": "Drive Retention",
      "budgetType": "Daily",
      "budget": 8,
      "impressions": 167927,
      "clicks": 2796,
      "plays": 595,
      "spent": 52.58,
      "ctr": 1.67,
      "playRate": 0.35,
      "cpc": 0.018,
      "cpp": 0.088
    },
    {
      "name": "Drive Retention_Yopiverso_06232025_11:56AM",
      "campaignId": "eef3375f-f067-46b9-95cf-02c66c4f4fab",
      "startDate": "2025-06-23",
      "endDate": "2025-06-29",
      "objective": "Drive Retention",
      "budgetType": "Daily",
      "budget": 8,
      "impressions": 191083,
      "clicks": 3290,
      "plays": 707,
      "spent": 52.31,
      "ctr": 1.72,
      "playRate": 0.37,
      "cpc": 0.015,
      "cpp": 0.073
    },
    {
      "name": "Maximize Plays_New Ads semana 4",
      "campaignId": "191c0be5-6dae-493b-8f10-95701ba79658",
      "startDate": "2025-06-16",
      "endDate": "2025-06-22",
      "objective": "Maximize Plays",
      "budgetType": "Lifetime",
      "budget": 200,
      "impressions": 661656,
      "clicks": 8128,
      "plays": 1649,
      "spent": 200,
      "ctr": 1.23,
      "playRate": 0.25,
      "cpc": 0.024,
      "cpp": 0.121
    },
    {
      "name": "Maximize Plays_Yopiverso_05262025_03:48PM",
      "campaignId": "9c8791f3-e34e-472d-879f-c4416744a6e4",
      "startDate": "2025-05-26",
      "endDate": "2025-06-01",
      "objective": "Maximize Plays",
      "budgetType": "Daily",
      "budget": 80,
      "impressions": 1679195,
      "clicks": 26439,
      "plays": 5372,
      "spent": 365.54,
      "ctr": 1.57,
      "playRate": 0.32,
      "cpc": 0.013,
      "cpp": 0.068
    },
    {
      "name": "Maximize Plays_Yopiverso_05282025_12:11PM (2)",
      "campaignId": "500eeb3d-e147-4f98-9353-857c873f6ae8",
      "startDate": "2025-05-28",
      "endDate": null,
      "objective": "Maximize Plays",
      "budgetType": "Daily",
      "budget": 200,
      "impressions": 4164161,
      "clicks": 55174,
      "plays": 12417,
      "spent": 1143.06,
      "ctr": 1.32,
      "playRate": 0.3,
      "cpc": 0.02,
      "cpp": 0.092
    },
    {
      "name": "Maximize Plays_Yopiverso_06022025_08:48AM",
      "campaignId": "3ad77ef6-fa0f-457d-886b-747685df5d68",
      "startDate": "2025-06-02",
      "endDate": "2025-06-08",
      "objective": "Maximize Plays",
      "budgetType": "Daily",
      "budget": 138,
      "impressions": 3111275,
      "clicks": 33135,
      "plays": 7942,
      "spent": 606.53,
      "ctr": 1.06,
      "playRate": 0.26,
      "cpc": 0.018,
      "cpp": 0.076
    },
    {
      "name": "Maximize Plays_Yopiverso_06022025_11:04AM",
      "campaignId": "cd8048dc-b7ec-46e9-ae72-46a866bfc315",
      "startDate": "2025-06-02",
      "endDate": "2025-06-08",
      "objective": "Maximize Plays",
      "budgetType": "Daily",
      "budget": 157,
      "impressions": 2856647,
      "clicks": 40202,
      "plays": 9212,
      "spent": 659.69,
      "ctr": 1.41,
      "playRate": 0.32,
      "cpc": 0.016,
      "cpp": 0.071
    },
    {
      "name": "New Ads 1",
      "campaignId": "cda7b133-1a52-4457-97a0-ba0e4949a4b1",
      "startDate": "2025-06-09",
      "endDate": null,
      "objective": "Maximize Plays",
      "budgetType": "Daily",
      "budget": 234,
      "impressions": 5202183,
      "clicks": 54111,
      "plays": 11533,
      "spent": 1527.72,
      "ctr": 1.04,
      "playRate": 0.22,
      "cpc": 0.028,
      "cpp": 0.132
    },
    {
      "name": "New Ads 2",
      "campaignId": "1ee1b7a0-aa7c-4700-9b8a-14e22bd3c85b",
      "startDate": "2025-06-09",
      "endDate": null,
      "objective": "Maximize Plays",
      "budgetType": "Daily",
      "budget": 234,
      "impressions": 4798602,
      "clicks": 49995,
      "plays": 10761,
      "spent": 1327.48,
      "ctr": 1.04,
      "playRate": 0.22,
      "cpc": 0.026,
      "cpp": 0.123
    },
    {
      "name": "New Ads 3",
      "campaignId": "24e30527-de83-46b6-bdb6-8ae8e4ea8b87",
      "startDate": "2025-06-09",
      "endDate": null,
      "objective": "Maximize Plays",
      "budgetType": "Daily",
      "budget": 234,
      "impressions": 1736602,
      "clicks": 18081,
      "plays": 3886,
      "spent": 466.62,
      "ctr": 1.04,
      "playRate": 0.22,
      "cpc": 0.026,
      "cpp": 0.12
    },
    {
      "name": "New Ads 4",
      "campaignId": "a4e7e86b-e65a-4fc2-bbfa-e58b93e79e5c",
      "startDate": "2025-06-23",
      "endDate": null,
      "objective": "Maximize Plays",
      "budgetType": "Daily",
      "budget": 100,
      "impressions": 724994,
      "clicks": 7532,
      "plays": 1620,
      "spent": 168.25,
      "ctr": 1.04,
      "playRate": 0.22,
      "cpc": 0.022,
      "cpp": 0.104
    },
    {
      "name": "New Ads 5",
      "campaignId": "e8eb2b7f-f0aa-4a55-8fe1-b2c5a9651b17",
      "startDate": "2025-06-30",
      "endDate": null,
      "objective": "Maximize Plays",
      "budgetType": "Daily",
      "budget": 100,
      "impressions": 373133,
      "clicks": 3879,
      "plays": 832,
      "spent": 82.06,
      "ctr": 1.04,
      "playRate": 0.22,
      "cpc": 0.021,
      "cpp": 0.099
    },
    {
      "name": "Awareness - 05/26/2025",
      "campaignId": "b8ed7350-3671-4589-85dd-758369b0c0e1",
      "startDate": "2025-05-26",
      "endDate": "2025-06-02",
      "objective": "Awareness",
      "budgetType": "Lifetime",
      "budget": 100,
      "impressions": 45646,
      "clicks": 0,
      "plays": 0,
      "spent": 91.29,
      "ctr": 0,
      "playRate": 0,
      "cpc": 0,
      "cpp": 0
    },
    {
      "name": "Portal 1",
      "campaignId": "c0896286-c37f-4989-aad6-ec5e6f7ede9e",
      "startDate": "2025-06-02",
      "endDate": "2025-06-09",
      "objective": "Visits",
      "budgetType": "Daily",
      "budget": 100,
      "impressions": 7555,
      "clicks": 0,
      "plays": 3306,
      "spent": 395.45,
      "ctr": 0,
      "playRate": 43.76,
      "cpc": 0,
      "cpp": 0.11
    },
    {
      "name": "Portal 1 semana 4",
      "campaignId": "cb8f208d-1d33-4b27-ab6b-e87982cb2ca1",
      "startDate": "2025-06-16",
      "endDate": "2025-06-23",
      "objective": "Visits",
      "budgetType": "Lifetime",
      "budget": 50,
      "impressions": 1826,
      "clicks": 0,
      "plays": 1138,
      "spent": 45.99,
      "ctr": 0,
      "playRate": 62.32,
      "cpc": 0,
      "cpp": 0.04
    },
    {
      "name": "Portal 2",
      "campaignId": "67f3c87f-a250-4b9f-bd62-a0e389422b56",
      "startDate": "2025-06-02",
      "endDate": "2025-06-09",
      "objective": "Visits",
      "budgetType": "Daily",
      "budget": 100,
      "impressions": 36552,
      "clicks": 0,
      "plays": 20484,
      "spent": 596.7,
      "ctr": 0,
      "playRate": 56.04,
      "cpc": 0,
      "cpp": 0.02
    },
    {
      "name": "Portal 2 semana 4",
      "campaignId": "7fb730cb-c6e4-4f0c-b42a-179d0d2d6788",
      "startDate": "2025-06-16",
      "endDate": "2025-06-23",
      "objective": "Visits",
      "budgetType": "Lifetime",
      "budget": 50,
      "impressions": 2193,
      "clicks": 0,
      "plays": 1373,
      "spent": 56.67,
      "ctr": 0,
      "playRate": 62.61,
      "cpc": 0,
      "cpp": 0.04
    },
    {
      "name": "Portal 3 semana 4",
      "campaignId": "9dad4200-fcff-4403-b1dd-8fe4e0ef6fcf",
      "startDate": "2025-06-16",
      "endDate": "2025-06-23",
      "objective": "Visits",
      "budgetType": "Lifetime",
      "budget": 50,
      "impressions": 3586,
      "clicks": 0,
      "plays": 1886,
      "spent": 56.62,
      "ctr": 0,
      "playRate": 52.59,
      "cpc": 0,
      "cpp": 0.03
    },
    {
      "name": "Portal 4 semana 4",
      "campaignId": "2d037992-ae37-4881-b2bd-9299b38a0a74",
      "startDate": "2025-06-16",
      "endDate": "2025-06-23",
      "objective": "Visits",
      "budgetType": "Lifetime",
      "budget": 50,
      "impressions": 2702,
      "clicks": 0,
      "plays": 1500,
      "spent": 54.55,
      "ctr": 0,
      "playRate": 55.51,
      "cpc": 0,
      "cpp": 0.03
    },
    {
      "name": "Portal Ads Yopiverso 26-05-2025",
      "campaignId": "1abb4cc7-c507-43b0-865e-8b2d4fec0f1c",
      "startDate": "2025-05-26",
      "endDate": "2025-06-02",
      "objective": "Visits",
      "budgetType": "Lifetime",
      "budget": 200,
      "impressions": 4369,
      "clicks": 0,
      "plays": 2121,
      "spent": 179.16,
      "ctr": 0,
      "playRate": 48.55,
      "cpc": 0,
      "cpp": 0.08
    },
    {
      "name": "Portal Movil",
      "campaignId": "28647b80-3198-46db-9739-b89293a4253d",
      "startDate": "2025-06-09",
      "endDate": "2025-06-16",
      "objective": "Visits",
      "budgetType": "Lifetime",
      "budget": 100,
      "impressions": 5701,
      "clicks": 0,
      "plays": 3591,
      "spent": 107.73,
      "ctr": 0,
      "playRate": 62.99,
      "cpc": 0,
      "cpp": 0.03
    },
    {
      "name": "Sponsored",
      "campaignId": "59ea4319-4585-4b49-8c7d-ca778bac9a56",
      "startDate": "2025-06-02",
      "endDate": "2025-06-09",
      "objective": "Visits",
      "budgetType": "Daily",
      "budget": 20,
      "impressions": 995817,
      "clicks": 9916,
      "plays": 2356,
      "spent": 58.96,
      "ctr": 1,
      "playRate": 0.24,
      "cpc": 0,
      "cpp": 0.02
    },
    {
      "name": "Sponsored",
      "campaignId": "0a37a273-a2ef-4201-a0ab-5fd0b2a13697",
      "startDate": "2025-06-09",
      "endDate": "2025-06-16",
      "objective": "Visits",
      "budgetType": "Lifetime",
      "budget": 80,
      "impressions": 424167,
      "clicks": 4337,
      "plays": 947,
      "spent": 21.59,
      "ctr": 1.02,
      "playRate": 0.22,
      "cpc": 0,
      "cpp": 0.02
    },
    {
      "name": "Sponsored semana 4",
      "campaignId": "c1267103-1dd9-479e-bf29-1f41b8ae1708",
      "startDate": "2025-06-16",
      "endDate": "2025-06-23",
      "objective": "Visits",
      "budgetType": "Lifetime",
      "budget": 50,
      "impressions": 360677,
      "clicks": 4155,
      "plays": 779,
      "spent": 24.1,
      "ctr": 1.15,
      "playRate": 0.22,
      "cpc": 0,
      "cpp": 0.03
    },
    {
      "name": "Visits - 05/26/2025 Portal Movil todas las edades",
      "campaignId": "beb6b1db-b096-4b78-a8ce-8b7cc1a278df",
      "startDate": "2025-05-26",
      "endDate": "2025-06-02",
      "objective": "Visits",
      "budgetType": "Lifetime",
      "budget": 200,
      "impressions": 8449,
      "clicks": 0,
      "plays": 5959,
      "spent": 178.77,
      "ctr": 0,
      "playRate": 70.53,
      "cpc": 0,
      "cpp": 0.03
    },
    {
      "name": "sponsor ads Yopiverso 26-05-2025",
      "campaignId": "a500a65f-1368-4f93-8219-6a167d7ff00b",
      "startDate": "2025-05-26",
      "endDate": "2025-06-02",
      "objective": "Visits",
      "budgetType": "Lifetime",
      "budget": 200,
      "impressions": 108697,
      "clicks": 1368,
      "plays": 213,
      "spent": 5.25,
      "ctr": 1.26,
      "playRate": 0.2,
      "cpc": 0,
      "cpp": 0.02
    },
    {
      "name": "Portal Sponsored Weekly 1",
      "campaignId": "b2f8d1a6-3e5c-4b89-9f7a-c8d2e1f4g5h6",
      "startDate": "2025-06-23",
      "endDate": "2025-06-30",
      "objective": "Visits",
      "budgetType": "Lifetime",
      "budget": 60,
      "impressions": 285432,
      "clicks": 3298,
      "plays": 618,
      "spent": 19.84,
      "ctr": 1.16,
      "playRate": 0.22,
      "cpc": 0.006,
      "cpp": 0.032
    },
    {
      "name": "Portal Sponsored Weekly 2",
      "campaignId": "c3g9e2b7-4f6d-5c8a-0g8b-d9e3f2a5b6c7",
      "startDate": "2025-06-30",
      "endDate": "2025-07-07",
      "objective": "Visits",
      "budgetType": "Lifetime",
      "budget": 60,
      "impressions": 147216,
      "clicks": 1702,
      "plays": 319,
      "spent": 10.24,
      "ctr": 1.16,
      "playRate": 0.22,
      "cpc": 0.006,
      "cpp": 0.032
    },
    {
      "name": "Portal 5 semana 5",
      "campaignId": "d4h0f3c8-5g7e-6d9b-1h9c-e0f4a3b6c7d8",
      "startDate": "2025-06-23",
      "endDate": "2025-06-30",
      "objective": "Visits",
      "budgetType": "Lifetime",
      "budget": 50,
      "impressions": 2954,
      "clicks": 0,
      "plays": 1552,
      "spent": 58.76,
      "ctr": 0,
      "playRate": 52.54,
      "cpc": 0,
      "cpp": 0.038
    },
    {
      "name": "Portal 6 semana 5",
      "campaignId": "e5i1g4d9-6h8f-7e0c-2i0d-f1g5b4c7d8e9",
      "startDate": "2025-06-23",
      "endDate": "2025-06-30",
      "objective": "Visits",
      "budgetType": "Lifetime",
      "budget": 50,
      "impressions": 3126,
      "clicks": 0,
      "plays": 1643,
      "spent": 62.24,
      "ctr": 0,
      "playRate": 52.56,
      "cpc": 0,
      "cpp": 0.038
    },
    {
      "name": "Portal 7 semana 6",
      "campaignId": "f6j2h5e0-7i9g-8f1d-3j1e-g2h6c5d8e9f0",
      "startDate": "2025-06-30",
      "endDate": "2025-07-07",
      "objective": "Visits",
      "budgetType": "Lifetime",
      "budget": 50,
      "impressions": 1614,
      "clicks": 0,
      "plays": 848,
      "spent": 32.14,
      "ctr": 0,
      "playRate": 52.54,
      "cpc": 0,
      "cpp": 0.038
    },
    {
      "name": "Portal 8 semana 6",
      "campaignId": "g7k3i6f1-8j0h-9g2e-4k2f-h3i7d6e9f0g1",
      "startDate": "2025-06-30",
      "endDate": "2025-07-07",
      "objective": "Visits",
      "budgetType": "Lifetime",
      "budget": 50,
      "impressions": 1708,
      "clicks": 0,
      "plays": 897,
      "spent": 34.02,
      "ctr": 0,
      "playRate": 52.52,
      "cpc": 0,
      "cpp": 0.038
    },
    {
      "name": "Drive Retention_Weekly 2",
      "campaignId": "h8l4j7g2-9k1i-0h3f-5l3g-i4j8e7f0g1h2",
      "startDate": "2025-06-30",
      "endDate": "2025-07-06",
      "objective": "Drive Retention",
      "budgetType": "Daily",
      "budget": 8,
      "impressions": 98756,
      "clicks": 1699,
      "plays": 365,
      "spent": 27.06,
      "ctr": 1.72,
      "playRate": 0.37,
      "cpc": 0.016,
      "cpp": 0.074
    },
    {
      "name": "Maximize Plays_Weekly Update 1",
      "campaignId": "i9m5k8h3-0l2j-1i4g-6m4h-j5k9f8g1h2i3",
      "startDate": "2025-07-02",
      "endDate": null,
      "objective": "Maximize Plays",
      "budgetType": "Daily",
      "budget": 150,
      "impressions": 542168,
      "clicks": 5634,
      "plays": 1209,
      "spent": 126.48,
      "ctr": 1.04,
      "playRate": 0.22,
      "cpc": 0.022,
      "cpp": 0.105
    },
    {
      "name": "Maximize Plays_Weekly Update 2",
      "campaignId": "j0n6l9i4-1m3k-2j5h-7n5i-k6l0g9h2i3j4",
      "startDate": "2025-07-02",
      "endDate": null,
      "objective": "Maximize Plays",
      "budgetType": "Daily",
      "budget": 150,
      "impressions": 498743,
      "clicks": 5182,
      "plays": 1112,
      "spent": 116.32,
      "ctr": 1.04,
      "playRate": 0.22,
      "cpc": 0.022,
      "cpp": 0.105
    }
  ]
}
